dxlmispservice/__init__.py
dxlmispservice/__main__.py
dxlmispservice/_requesthandlers.py
dxlmispservice/_version.py
dxlmispservice/app.py
dxlmispservice/_config/__init__.py
dxlmispservice/_config/app/__init__.py
dxlmispservice/_config/app/dxlclient.config
dxlmispservice/_config/app/dxlmispservice.config
dxlmispservice/_config/app/logging.config
dxlmispservice/_config/sample/__init__.py
dxlmispservice/_config/sample/dxlclient.config
dxlmispservice/_config/sample/dxlmispservice.config
dxlmispservice-0.1.5.dist-info/LICENSE
dxlmispservice-0.1.5.dist-info/METADATA
dxlmispservice-0.1.5.dist-info/WHEEL
dxlmispservice-0.1.5.dist-info/top_level.txt
dxlmispservice-0.1.5.dist-info/RECORD
