Metadata-Version: 2.1
Name: dxlmispservice
Version: 0.1.5
Summary: MISP DXL Python Service
Home-page: http://www.mcafee.com
Author: McAfee LLC
License: Apache License 2.0
Keywords: opendxl,dxl,mcafee,service,misp
Platform: UNKNOWN
Classifier: Development Status :: 4 - Beta
Classifier: Topic :: Software Development :: Libraries :: Python Modules
Classifier: License :: OSI Approved :: Apache Software License
Classifier: Programming Language :: Python
Classifier: Programming Language :: Python :: 2
Classifier: Programming Language :: Python :: 2.7
Classifier: Programming Language :: Python :: 3
Classifier: Programming Language :: Python :: 3.4
Classifier: Programming Language :: Python :: 3.5
Classifier: Programming Language :: Python :: 3.6
Classifier: Programming Language :: Python :: 3.7
Requires-Python: >=2.7.9,!=3.0.*,!=3.1.*,!=3.2.*,!=3.3.*
Requires-Dist: dxlbootstrap (>=0.2.0)
Requires-Dist: dxlclient (>=4.1.0.184)
Requires-Dist: enum34
Requires-Dist: pymisp (==2.4.111.2)
Requires-Dist: pyzmq
Provides-Extra: dev
Requires-Dist: mock ; extra == 'dev'
Requires-Dist: nose ; extra == 'dev'
Requires-Dist: requests-mock ; extra == 'dev'
Requires-Dist: astroid (<2.3.0) ; extra == 'dev'
Requires-Dist: pylint (<=2.3.1) ; extra == 'dev'
Requires-Dist: sphinx ; extra == 'dev'
Provides-Extra: test
Requires-Dist: mock ; extra == 'test'
Requires-Dist: nose ; extra == 'test'
Requires-Dist: requests-mock ; extra == 'test'
Requires-Dist: astroid (<2.3.0) ; extra == 'test'
Requires-Dist: pylint (<=2.3.1) ; extra == 'test'
